pydantic_toolbox/__init__.py
pydantic_toolbox/errors.py
pydantic_toolbox/types.py
pydantic_toolbox-0.1.0.dist-info/LICENSE
pydantic_toolbox-0.1.0.dist-info/WHEEL
pydantic_toolbox-0.1.0.dist-info/METADATA
pydantic_toolbox-0.1.0.dist-info/RECORD
