Metadata-Version: 2.1
Name: pydantic-toolbox
Version: 0.1.0
Summary: Usefool tools and types for pydantic that for some reasons are not shipped with it
Author: Bobronium
Author-email: appkiller16@gmail.com
Requires-Python: >=3.10,<4.0
Classifier: Programming Language :: Python :: 3
Classifier: Programming Language :: Python :: 3.10
Requires-Dist: pydantic (>=1.9.0,<2.0.0)
